prompts/__init__.py
prompts/improve_prompt.py
prompts/system_prompt.py
scores/__init__.py
scores/perplexity_score.py
tests/__init__.py
tests/test_improve_prompt.py
tests/test_perplexity_score.py
tests/test_system_prompt.py
prompt_program-0.1.2.dist-info/LICENSE.txt
prompt_program-0.1.2.dist-info/METADATA
prompt_program-0.1.2.dist-info/WHEEL
prompt_program-0.1.2.dist-info/top_level.txt
prompt_program-0.1.2.dist-info/RECORD
