Metadata-Version: 2.1
Name: prompt_program
Version: 0.1.2
Summary: A library for creating perfectly intended prompts.
Author: Krishna Rathore
Author-email: krishnarathore393@gmail.com
Classifier: Programming Language :: Python :: 3
Classifier: License :: OSI Approved :: MIT License
Classifier: Operating System :: OS Independent
Requires-Python: >=3.6
License-File: LICENSE.txt
